databricks_industrial_automation_suite/README.md
databricks_industrial_automation_suite/__init__.py
databricks_industrial_automation_suite/certificate_management/__init__.py
databricks_industrial_automation_suite/certificate_management/certificate_manager.py
databricks_industrial_automation_suite/integrations/__init__.py
databricks_industrial_automation_suite/integrations/opcua.py
databricks_industrial_automation_suite/models/__init__.py
databricks_industrial_automation_suite/utils/.gitkeep
databricks_industrial_automation_suite/utils/__init__.py
databricks_industrial_automation_suite/utils/logger.py
databricks_industrial_automation_suite-0.0.3.dist-info/LICENSE
databricks_industrial_automation_suite-0.0.3.dist-info/METADATA
databricks_industrial_automation_suite-0.0.3.dist-info/WHEEL
databricks_industrial_automation_suite-0.0.3.dist-info/RECORD
