Metadata-Version: 2.1
Name: databricks-industrial-automation-suite
Version: 0.0.3
Summary: A comprehensive library designed to support all major industrial automation protocols within the Databricks ecosystem.
Author: Irfan Ghat
Author-email: irfanghat@gmail.com
Requires-Python: >=3.9
Classifier: Programming Language :: Python :: 3
Classifier: Programming Language :: Python :: 3.9
Classifier: Programming Language :: Python :: 3.10
Classifier: Programming Language :: Python :: 3.11
Requires-Dist: asyncio
Requires-Dist: asyncua
Requires-Dist: cryptography
Requires-Dist: lxml
Requires-Dist: python-dateutil
Requires-Dist: pytz
Requires-Dist: tabulate
